ritc/__init__.py
ritc/py.typed
ritc-1.0.0.dist-info/LICENSE
ritc-1.0.0.dist-info/METADATA
ritc-1.0.0.dist-info/WHEEL
ritc-1.0.0.dist-info/top_level.txt
ritc-1.0.0.dist-info/RECORD
