Metadata-Version: 2.1
Name: ritc
Version: 1.0.0
Summary: A Python library for interactions with Rotman Interactive Trader Market Simulator Client Application via REST exchange API
Home-page: https://github.com/AussieSeaweed/ritc
Author: Juho Kim
Author-email: juho-kim@outlook.com
License: MIT
Project-URL: Documentation, https://ritc.readthedocs.io/en/latest/
Project-URL: Source, https://github.com/AussieSeaweed/ritc
Project-URL: Tracker, https://github.com/AussieSeaweed/ritc/issues
Keywords: rotman,rit,bmo,uoft
Classifier: Intended Audience :: Developers
Classifier: Intended Audience :: Education
Classifier: Intended Audience :: End Users/Desktop
Classifier: Intended Audience :: Financial and Insurance Industry
Classifier: Intended Audience :: Information Technology
Classifier: Topic :: Education
Classifier: License :: OSI Approved :: MIT License
Classifier: Operating System :: OS Independent
Classifier: Programming Language :: Python
Classifier: Programming Language :: Python :: 3
Classifier: Programming Language :: Python :: 3 :: Only
Classifier: Programming Language :: Python :: 3.9
Classifier: Programming Language :: Python :: 3.10
Classifier: Programming Language :: Python :: 3.11
Classifier: Programming Language :: Python :: 3.12
Requires-Python: >=3.9
License-File: LICENSE
Requires-Dist: requests (~=2.28.2)
